rms_rpc_core/__init__.py
rms_rpc_core/rpc_abstract.py
rms_rpc_core/rpc_client.py
rms_rpc_core/rpc_method.py
rms_rpc_core/rpc_server.py
rms_rpc_core/utils.py
rms_rpc_core/base/__init__.py
rms_rpc_core/base/registry.py
rms_rpc_core/base/rpc_base.py
rms_rpc_core/base/rpc_exceptions.py
rms_rpc_core-1.0.2.dist-info/METADATA
rms_rpc_core-1.0.2.dist-info/WHEEL
rms_rpc_core-1.0.2.dist-info/top_level.txt
rms_rpc_core-1.0.2.dist-info/RECORD
