Metadata-Version: 2.1
Name: rms-rpc-core
Version: 1.0.2
Summary: Библиотека для RPC.
Home-page: https://gitlab.com/requirements-managment-systems/rms_rpc_core
Author: Prokofev D.D.
Author-email: skily02@gmail.com
Classifier: Development Status :: 3 - Alpha
Classifier: Operating System :: MacOS
Classifier: Operating System :: POSIX :: Linux
Classifier: Topic :: Scientific/Engineering
Classifier: License :: OSI Approved :: MIT License
Classifier: Programming Language :: Python
Classifier: Programming Language :: Python :: 3
Classifier: Programming Language :: Python :: 3.11
Classifier: Topic :: Internet :: WWW/HTTP
Requires-Python: >=3.11
Requires-Dist: aio-pika==9.5.5
Requires-Dist: msgpack==1.1.0
Requires-Dist: pydantic>=1.10.2
Requires-Dist: pyhocon>=0.3.59
Requires-Dist: marshmallow-dataclass>=8.5.3
Requires-Dist: marshmallow-enum>=1.5.1
Requires-Dist: setuptools<81.0.0,>=65.5.0
Requires-Dist: typeguard>=2.13.3
Provides-Extra: dev
Requires-Dist: flake8==7.2.0; extra == "dev"
Requires-Dist: types-orjson; extra == "dev"
Requires-Dist: types-ujson; extra == "dev"
Requires-Dist: types-dataclasses; extra == "dev"
Requires-Dist: isort==6.0.1; extra == "dev"
Requires-Dist: mypy==1.15.0; extra == "dev"
Requires-Dist: mypy-extensions==1.1.0; extra == "dev"
Requires-Dist: wemake-python-styleguide>=1.1.0; extra == "dev"
Requires-Dist: pytest>=7.0.1; extra == "dev"
Requires-Dist: pytest-asyncio==0.18.2; extra == "dev"
Requires-Dist: pytest-aiohttp>=1.0.4; extra == "dev"
Requires-Dist: pytest-testdox>=3.0.0; extra == "dev"
Requires-Dist: pytest-cov>=3.0.0; extra == "dev"
